MANIFEST.in
README.rst
setup.cfg
setup.py
webvis/VisVars.py
webvis/VisWorker.py
webvis/__about__.py
webvis/__init__.py
webvis/http_server.py
webvis/interface.py
webvis/main.py
webvis.egg-info/PKG-INFO
webvis.egg-info/SOURCES.txt
webvis.egg-info/dependency_links.txt
webvis.egg-info/requires.txt
webvis.egg-info/top_level.txt
webvis/front_build/index.bundle.js
webvis/front_build/index.html
webvis/helpers/AttrDict.py
webvis/helpers/__init__.py
webvis/helpers/threaded.py
webvis/modules/Base.py
webvis/modules/__init__.py
webvis/modules/installed/__init__.py
webvis/modules/installed/WebPage/__init__.py
webvis/modules/installed/WebPage/back.py
webvis/websocket/__init__.py
webvis/websocket/message_gen.py
webvis/websocket/test_ws_server.py
webvis/websocket/ws_client.py
webvis/websocket/ws_server.py