Metadata-Version: 2.1
Name: webvis
Version: 0.0.9
Summary: A live two-way data binder for python
Home-page: https://github.com/DaniloZZZ/pywebviz
Author: Dan Lykov
Author-email: lkvdan@gmail.com
License: MIT
Keywords: tools,data,framework,visualization
Platform: UNKNOWN
Requires-Python: >=3.3
